oorpc/MyInfo.py
oorpc/__init__.py
oorpc/__main__.py
oorpc/channel.py
oorpc/cipher.py
oorpc/common.py
oorpc/config.py
oorpc/connection.py
oorpc/file_receiver.py
oorpc/file_receiver.xidl
oorpc/file_receiver_service.py
oorpc/file_stream.py
oorpc/find.py
oorpc/handshake.py
oorpc/interface.py
oorpc/log.py
oorpc/peer.py
oorpc/peer.xidl
oorpc/peer_service.py
oorpc/progress_bar.py
oorpc/rsa_key.py
oorpc/xfmt.py
oorpc/xidl/Peer.py
oorpc/xidl/Peer.xidl
oorpc/xidl/convert.py
oorpc/xidl/convert2.py
oorpc/xidl/convert3.py
oorpc/xidl/convert3_comment.py
oorpc-0.1.4.dist-info/LICENSE
oorpc-0.1.4.dist-info/WHEEL
oorpc-0.1.4.dist-info/entry_points.txt
oorpc-0.1.4.dist-info/METADATA
oorpc-0.1.4.dist-info/RECORD
